evennia_wiki/__init__.py
evennia_wiki/admin.py
evennia_wiki/apps.py
evennia_wiki/forms.py
evennia_wiki/managers.py
evennia_wiki/markdown_engine.py
evennia_wiki/models.py
evennia_wiki/tests.py
evennia_wiki/urls.py
evennia_wiki/views.py
evennia_wiki/migrations/0001_initial.py
evennia_wiki/migrations/0002_add_title_to_pages.py
evennia_wiki/migrations/0003_add_permissions.py
evennia_wiki/migrations/__init__.py
evennia_wiki/template_tags/__init__.py
evennia_wiki/template_tags/add_class.py
evennia_wiki/templates/wiki/_tabs.html
evennia_wiki/templates/wiki/base.html
evennia_wiki/templates/wiki/cant_read.html
evennia_wiki/templates/wiki/edit.html
evennia_wiki/templates/wiki/page.html
evennia_wiki-0.2.dist-info/LICENSE
evennia_wiki-0.2.dist-info/METADATA
evennia_wiki-0.2.dist-info/WHEEL
evennia_wiki-0.2.dist-info/top_level.txt
evennia_wiki-0.2.dist-info/RECORD
