Metadata-Version: 2.1
Name: evennia-wiki
Version: 0.2
Summary: A simple Django app to add a wiki to Evennia
Home-page: UNKNOWN
Author: Vincent Le Goff
Author-email: vincent.legoff.srs@gmail.com
License: BSD License
Platform: UNKNOWN
Classifier: Environment :: Web Environment
Classifier: Framework :: Django
Classifier: Framework :: Django :: 1.11
Classifier: Intended Audience :: Developers
Classifier: License :: OSI Approved :: BSD License
Classifier: Operating System :: OS Independent
Classifier: Programming Language :: Python :: 2
Classifier: Topic :: Internet :: WWW/HTTP
Classifier: Topic :: Internet :: WWW/HTTP :: Dynamic Content
Requires-Dist: markdown
Requires-Dist: BeautifulSoup4
